MANIFEST.in
README.rst
setup.py
Mopidy_Yandexmusic.egg-info/PKG-INFO
Mopidy_Yandexmusic.egg-info/SOURCES.txt
Mopidy_Yandexmusic.egg-info/dependency_links.txt
Mopidy_Yandexmusic.egg-info/entry_points.txt
Mopidy_Yandexmusic.egg-info/not-zip-safe
Mopidy_Yandexmusic.egg-info/requires.txt
Mopidy_Yandexmusic.egg-info/top_level.txt
mopidy_yandexmusic/__init__.py
mopidy_yandexmusic/backend.py
mopidy_yandexmusic/caches.py
mopidy_yandexmusic/classes.py
mopidy_yandexmusic/ext.conf
mopidy_yandexmusic/library_provider.py
mopidy_yandexmusic/playback_provider.py
mopidy_yandexmusic/playlist_provider.py