Metadata-Version: 1.1
Name: Mopidy-Yandexmusic
Version: 0.0.6
Summary: Yandex Music plugin for Mopidy
Home-page: UNKNOWN
Author: Irokez Petrovic
Author-email: irokezpetrovic@gmail.com
License: Apache License, Version 2.0
Platform: UNKNOWN
Classifier: Environment :: No Input/Output (Daemon)
Classifier: Intended Audience :: End Users/Desktop
Classifier: License :: OSI Approved :: Apache Software License
Classifier: Operating System :: OS Independent
Classifier: Programming Language :: Python :: 3
Classifier: Topic :: Multimedia :: Sound/Audio :: Players
